Metadata-Version: 2.4
Name: django-redirects
Version: 0.9.0
Summary: django redirects as they should be, with full control.
Author-email: Fabio Caccamo <fabio.caccamo@gmail.com>
Maintainer-email: Fabio Caccamo <fabio.caccamo@gmail.com>
License: MIT License
Project-URL: Homepage, https://github.com/fabiocaccamo/django-redirects
Project-URL: Download, https://github.com/fabiocaccamo/django-redirects/releases
Project-URL: Documentation, https://github.com/fabiocaccamo/django-redirects#readme
Project-URL: Issues, https://github.com/fabiocaccamo/django-redirects/issues
Project-URL: Funding, https://github.com/sponsors/fabiocaccamo/
Project-URL: Twitter, https://twitter.com/fabiocaccamo
Keywords: django,admin,redirects,redirect,permanent,temporary,301,302,303,307,308,exact,prefix,regex
Classifier: Development Status :: 5 - Production/Stable
Classifier: Environment :: Web Environment
Classifier: Framework :: Django
Classifier: Framework :: Django :: 4.0
Classifier: Framework :: Django :: 4.1
Classifier: Framework :: Django :: 4.2
Classifier: Framework :: Django :: 5.0
Classifier: Framework :: Django :: 5.1
Classifier: Framework :: Django :: 5.2
Classifier: Intended Audience :: Developers
Classifier: License :: OSI Approved :: MIT License
Classifier: Natural Language :: English
Classifier: Operating System :: OS Independent
Classifier: Programming Language :: Python :: 3
Classifier: Programming Language :: Python :: 3.10
Classifier: Programming Language :: Python :: 3.11
Classifier: Programming Language :: Python :: 3.12
Classifier: Programming Language :: Python :: 3.13
Classifier: Topic :: Software Development :: Build Tools
License-File: LICENSE.txt
Dynamic: license-file
